fuzzysearch-0.8.1.dist-info/RECORD
fuzzysearch-0.8.1.dist-info/WHEEL
fuzzysearch-0.8.1.dist-info/top_level.txt
fuzzysearch-0.8.1.dist-info/METADATA
fuzzysearch-0.8.1.dist-info/licenses/LICENSE
fuzzysearch-0.8.1.dist-info/licenses/AUTHORS.rst
fuzzysearch/_common.cpython-311-darwin.so
fuzzysearch/no_deletions.py
fuzzysearch/__init__.py
fuzzysearch/substitutions_only.py
fuzzysearch/_substitutions_only.cpython-311-darwin.so
fuzzysearch/common.py
fuzzysearch/levenshtein.py
fuzzysearch/generic_search.py
fuzzysearch/levenshtein_ngram.py
fuzzysearch/search_exact.py
